ained/Data/exampleData.json
ained/Data/jasonSchema.json
ained/TauswortheInC/README.md
ained/TauswortheInC/libtausworthe.so
ained/TauswortheInC/tausworthe.c
ained/TauswortheInC/tausworthe_wrapper.c
ained/__init__.py
ained/board.py
ained/calculator.py
ained/dipole.py
ained/display.py
ained/fixedpoint_config.py
ained/generator.py
ained/historymanager.py
ained/main.py
ained/number_gen.py
ained/processJson.py
ained/test/Test_Data.txt
ained/test/__init__.py
ained/test/test_board.py
ained/test/test_dipole.py
ained/test/test_fixedpoint.py
ained/test/test_generator.py
ained/test/test_utils.py
ained-0.2.3.dist-info/METADATA
ained-0.2.3.dist-info/WHEEL
ained-0.2.3.dist-info/entry_points.txt
ained-0.2.3.dist-info/RECORD
