Metadata-Version: 2.1
Name: ained
Version: 0.2.3
Summary: Stochastic Synchrony Functional Model in Python
Author: aschroede
Author-email: aschroed@ualberta.ca
Requires-Python: >=3.10,<4.0
Classifier: Programming Language :: Python :: 3
Classifier: Programming Language :: Python :: 3.10
Classifier: Programming Language :: Python :: 3.11
Classifier: Programming Language :: Python :: 3.12
Requires-Dist: fxpmath (>=0.4.9,<0.5.0)
Requires-Dist: jsonschema (>=4.21.1,<5.0.0)
Requires-Dist: matplotlib (>=3.8.4,<4.0.0)
Requires-Dist: tk (>=0.1.0,<0.2.0)
Requires-Dist: typer[all] (>=0.12.3,<0.13.0)
